Workbook

Sheet Ipotesi
A1: CasaZen - modello economico 36 mesi (nov 2026 - ott 2029). Celle gialle = ipotesi modificabili.
A2: Fonti: PR #526 §5-§6 per prezzi e costi unitari; il resto è IPOTESI (vedi business-plan.md §10).
B4: Scenario attivo (1-3) | C4: 3
A6: Prezzi e costi unitari
B7: Listino tutto compreso 10-49 unità (€/unità) | C7: 15
B8: Listino tutto compreso 50-149 unità (€/unità) | C8: 14
B9: Listino tutto compreso 150-399 unità (€/unità) | C9: 13
B10: Verifiche d'identità per unità al mese | C10: 8
B11: Canone Founding Partner (€/unità) | C11: 6.92
B12: NextPax minimo mensile (€) | C12: 350
B13: Unità incluse nel minimo NextPax | C13: 50
B14: NextPax oltre il minimo (€/unità) | C14: 3.15
B15: SDI, AI, video (€/unità) | C15: 0.4
B16: Costo di una verifica (€) | C16: 0.48
B17: Canone B2C (€/host) - IPOTESI | C17: 29
B18: Unità medie per host B2C - IPOTESI | C18: 2
A20: Costi fissi
B21: Piattaforma prima del go-live (€/mese) | C21: 205
B22: Piattaforma in produzione, senza NextPax (€/mese) | C22: 375
B23: Vercel Pro (€/mese) | C23: 20
B24: Commercialista, PEC, banca (€/mese) - IPOTESI | C24: 150
B25: Assicurazioni (€/mese) - IPOTESI | C25: 100
B26: Mese da cui la società ha costi | C26: 2
B27: Pareri e contratti una tantum (€) - IPOTESI | C27: 6000
B28: Mese della spesa una tantum | C28: 3
B29: Marketing e vendite dal go-live (€/mese) - IPOTESI | C29: 300
A31: Scenari | C31: A. Solo Quokka | D31: B. Ritardo | E31: C. Obiettivo | F31: Attivo
B32: Mese go-live Quokka (vuoto = mai) | C32: 7 | D32: 13 | E32: 7 | F32: =INDEX(C32:E32,1,$C$4) -> 7
B33: Unità Quokka | C33: 250 | D33: 250 | E33: 250 | F33: =INDEX(C33:E33,1,$C$4) -> 250
B34: Primo mese altri Founding Partner | C34: 99999 | D34: 16 | E34: 9 | F34: =INDEX(C34:E34,1,$C$4) -> 9
B35: Posti Founding Partner oltre Quokka | C35: 9 | D35: 9 | E35: 9 | F35: =INDEX(C35:E35,1,$C$4) -> 9
B36: Nuovi Founding Partner al mese | C36: 0 | D36: 0.25 | E36: 0.6 | F36: =INDEX(C36:E36,1,$C$4) -> 0.6
B37: Primo mese agenzie a listino | C37: 99999 | D37: 99999 | E37: 25 | F37: =INDEX(C37:E37,1,$C$4) -> 25
B38: Nuove agenzie a listino al mese | C38: 0 | D38: 0 | E38: 1 | F38: =INDEX(C38:E38,1,$C$4) -> 1
B39: Unità medie per agenzia | C39: 40 | D39: 40 | E39: 40 | F39: =INDEX(C39:E39,1,$C$4) -> 40
B40: Churn mensile agenzie a listino | C40: 0.01 | D40: 0.01 | E40: 0.01 | F40: =INDEX(C40:E40,1,$C$4) -> 0.01
B41: Primo mese B2C a pagamento | C41: 99999 | D41: 16 | E41: 10 | F41: =INDEX(C41:E41,1,$C$4) -> 10
B42: Nuovi host B2C al mese | C42: 0 | D42: 2 | E42: 6 | F42: =INDEX(C42:E42,1,$C$4) -> 6
B43: Churn mensile B2C | C43: 0.03 | D43: 0.03 | E43: 0.03 | F43: =INDEX(C43:E43,1,$C$4) -> 0.03
... B46: Costo supporto (€/mese) | C46: 3000 | D46: 3000 | E46: 3000 | F46: =INDEX(C46:E46,1,$C$4) -> 3000

Sheet Mensile
A1: Mese | B1: nov 2026 | C1: dic 2026 | D1: gen 2027 | E1: feb 2027 | F1: mar 2027 | G1: apr 2027 | H1: mag 2027 | I1: giu 2027 | J1: lug 2027 | K1: ago 2027 | L1: set 2027 | M1: ott 2027 | N1: nov 2027 | O1: dic 2027 | P1: gen 2028 | Q1: feb 2028 | R1: mar 2028 | S1: apr 2028 | T1: mag 2028 | U1: giu 2028 | V1: lug 2028 | W1: ago 2028 | X1: set 2028 | Y1: ott 2028 | Z1: nov 2028 | AA1: dic 2028 | AB1: gen 2029 | AC1: feb 2029 | AD1: mar 2029 | AE1: apr 2029 | AF1: mag 2029 | AG1: giu 2029 | AH1: lug 2029 | AI1: ago 2029 | AJ1: set 2029 | AK1: ott 2029
A2: Indice mese | B2: 1 | C2: 2 | D2: 3 | E2: 4 | F2: 5 | G2: 6 | H2: 7 | I2: 8 | J2: 9 | K2: 10 | L2: 11 | M2: 12 | N2: 13 | O2: 14 | P2: 15 | Q2: 16 | R2: 17 | S2: 18 | T2: 19 | U2: 20 | V2: 21 | W2: 22 | X2: 23 | Y2: 24 | Z2: 25 | AA2: 26 | AB2: 27 | AC2: 28 | AD2: 29 | AE2: 30 | AF2: 31 | AG2: 32 | AH2: 33 | AI2: 34 | AJ2: 35 | AK2: 36
A3: Quokka live (1/0) | B3: =IF(B2>=Ipotesi!$F$32,1,0) -> 0 | C3: =IF(C2>=Ipotesi!$F$32,1,0) -> 0 | D3: =IF(D2>=Ipotesi!$F$32,1,0) -> 0 | E3: =IF(E2>=Ipotesi!$F$32,1,0) -> 0 | F3: =IF(F2>=Ipotesi!$F$32,1,0) -> 0 | G3: =IF(G2>=Ipotesi!$F$32,1,0) -> 0 | H3: =IF(H2>=Ipotesi!$F$32,1,0) -> 1 | I3: =IF(I2>=Ipotesi!$F$32,1,0) -> 1 | ... AK3: =IF(AK2>=Ipotesi!$F$32,1,0) -> 1
A4: Unità Quokka | B4: =B3*Ipotesi!$F$33 -> 0 | C4: =C3*Ipotesi!$F$33 -> 0 | D4: =D3*Ipotesi!$F$33 -> 0 | E4: =E3*Ipotesi!$F$33 -> 0 | F4: =F3*Ipotesi!$F$33 -> 0 | G4: =G3*Ipotesi!$F$33 -> 0 | H4: =H3*Ipotesi!$F$33 -> 250 | I4: =I3*Ipotesi!$F$33 -> 250 | ... AK4: =AK3*Ipotesi!$F$33 -> 250
A5: Altri Founding Partner (agenzie) | B5: =IF(AND(B2>=Ipotesi!$F$34,B3=1),MIN(Ipotesi!$F$35,0+Ipotesi!$F$36),0) -> 0 | C5: =IF(AND(C2>=Ipotesi!$F$34,C3=1),MIN(Ipotesi!$F$35,B5+Ipotesi!$F$36),B5) -> 0 | D5: =IF(AND(D2>=Ipotesi!$F$34,D3=1),MIN(Ipotesi!$F$35,C5+Ipotesi!$F$36),C5) -> 0 | E5: =IF(AND(E2>=Ipotesi!$F$34,E3=1),MIN(Ipotesi!$F$35,D5+Ipotesi!$F$36),D5) -> 0 | F5: =IF(AND(F2>=Ipotesi!$F$34,F3=1),MIN(Ipotesi!$F$35,E5+Ipotesi!$F$36),E5) -> 0 | G5: =IF(AND(G2>=Ipotesi!$F$34,G3=1),MIN(Ipotesi!$F$35,F5+Ipotesi!$F$36),F5) -> 0 | H5: =IF(AND(H2>=Ipotesi!$F$34,H3=1),MIN(Ipotesi!$F$35,G5+Ipotesi!$F$36),G5) -> 0 | I5: =IF(AND(I2>=Ipotesi!$F$34,I3=1),MIN(Ipotesi!$F$35,H5+Ipotesi!$F$36),H5) -> 0 | J5: =IF(AND(J2>=Ipotesi!$F$34,J3=1),MIN(Ipotesi!$F$35,I5+Ipotesi!$F$36),I5) -> 0.6 | ... AK5: =IF(AND(AK2>=Ipotesi!$F$34,AK3=1),MIN(Ipotesi!$F$35,AJ5+Ipotesi!$F$36),AJ5) -> 9
A6: Agenzie a listino | B6: =IF(AND(B2>=Ipotesi!$F$37,B3=1),0*(1-Ipotesi!$F$40)+Ipotesi!$F$38,0) -> 0 | C6: =IF(AND(C2>=Ipotesi!$F$37,C3=1),B6*(1-Ipotesi!$F$40)+Ipotesi!$F$38,B6) -> 0 | D6: =IF(AND(D2>=Ipotesi!$F$37,D3=1),C6*(1-Ipotesi!$F$40)+Ipotesi!$F$38,C6) -> 0 | E6: =IF(AND(E2>=Ipotesi!$F$37,E3=1),D6*(1-Ipotesi!$F$40)+Ipotesi!$F$38,D6) -> 0 | F6: =IF(AND(F2>=Ipotesi!$F$37,F3=1),E6*(1-Ipotesi!$F$40)+Ipotesi!$F$38,E6) -> 0 | G6: =IF(AND(G2>=Ipotesi!$F$37,G3=1),F6*(1-Ipotesi!$F$40)+Ipotesi!$F$38,F6) -> 0 | H6: =IF(AND(H2>=Ipotesi!$F$37,H3=1),G6*(1-Ipotesi!$F$40)+Ipotesi!$F$38,G6) -> 0 | I6: =IF(AND(I2>=Ipotesi!$F$37,I3=1),H6*(1-Ipotesi!$F$40)+Ipotesi!$F$38,H6) -> 0 | J6: =IF(AND(J2>=Ipotesi!$F$37,J3=1),I6*(1-Ipotesi!$F$40)+Ipotesi!$F$38,I6) -> 0 | ... AK6: =IF(AND(AK2>=Ipotesi!$F$37,AK3=1),AJ6*(1-Ipotesi!$F$40)+Ipotesi!$F$38,AJ6) -> 11.361513
A7: Host B2C paganti | B7: =IF(B2>=Ipotesi!$F$41,0*(1-Ipotesi!$F$43)+Ipotesi!$F$42,0) -> 0 | C7: =IF(C2>=Ipotesi!$F$41,B7*(1-Ipotesi!$F$43)+Ipotesi!$F$42,B7) -> 0 | D7: =IF(D2>=Ipotesi!$F$41,C7*(1-Ipotesi!$F$43)+Ipotesi!$F$42,C7) -> 0 | E7: =IF(E2>=Ipotesi!$F$41,D7*(1-Ipotesi!$F$43)+Ipotesi!$F$42,D7) -> 0 | F7: =IF(F2>=Ipotesi!$F$41,E7*(1-Ipotesi!$F$43)+Ipotesi!$F$42,E7) -> 0 | G7: =IF(G2>=Ipotesi!$F$41,F7*(1-Ipotesi!$F$43)+Ipotesi!$F$42,F7) -> 0 | H7: =IF(H2>=Ipotesi!$F$41,G7*(1-Ipotesi!$F$43)+Ipotesi!$F$42,G7) -> 0 | I7: =IF(I2>=Ipotesi!$F$41,H7*(1-Ipotesi!$F$43)+Ipotesi!$F$42,H7) -> 0 | J7: =IF(J2>=Ipotesi!$F$41,I7*(1-Ipotesi!$F$43)+Ipotesi!$F$42,I7) -> 0 | ... AK7: =IF(AK2>=Ipotesi!$F$41,AJ7*(1-Ipotesi!$F$43)+Ipotesi!$F$42,AJ7) -> 112.1247
A8: Unità altri FP | B8: =B5*Ipotesi!$F$39 -> 0 | C8: =C5*Ipotesi!$F$39 -> 0 | D8: =D5*Ipotesi!$F$39 -> 0 | E8: =E5*Ipotesi!$F$39 -> 0 | F8: =F5*Ipotesi!$F$39 -> 0 | G8: =G5*Ipotesi!$F$39 -> 0 | H8: =H5*Ipotesi!$F$39 -> 0 | I8: =I5*Ipotesi!$F$39 -> 0 | ... AK8: =AK5*Ipotesi!$F$39 -> 360
A9: Unità a listino | B9: =B6*Ipotesi!$F$39 -> 0 | C9: =C6*Ipotesi!$F$39 -> 0 | D9: =D6*Ipotesi!$F$39 -> 0 | E9: =E6*Ipotesi!$F$39 -> 0 | F9: =F6*Ipotesi!$F$39 -> 0 | G9: =G6*Ipotesi!$F$39 -> 0 | H9: =H6*Ipotesi!$F$39 -> 0 | I9: =I6*Ipotesi!$F$39 -> 0 | ... AK9: =AK6*Ipotesi!$F$39 -> 454.46051
A10: Unità B2B totali | B10: =B4+B8+B9 -> 0 | C10: =C4+C8+C9 -> 0 | D10: =D4+D8+D9 -> 0 | E10: =E4+E8+E9 -> 0 | F10: =F4+F8+F9 -> 0 | G10: =G4+G8+G9 -> 0 | H10: =H4+H8+H9 -> 250 | I10: =I4+I8+I9 -> 250 | ... AK10: =AK4+AK8+AK9 -> 1064.4605
A11: Prezzo listino applicato (€/unità) | B11: =IF(Ipotesi!$F$39<50,Ipotesi!$C$7,IF(Ipotesi!$F$39<150,Ipotesi!$C$8,Ipotesi!$C$9)) -> 15 | C11: =IF(Ipotesi!$F$39<50,Ipotesi!$C$7,IF(Ipotesi!$F$39<150,Ipotesi!$C$8,Ipotesi!$C$9)) -> 15 | D11: =IF(Ipotesi!$F$39<50,Ipotesi!$C$7,IF(Ipotesi!$F$39<150,Ipotesi!$C$8,Ipotesi!$C$9)) -> 15 | E11: =IF(Ipotesi!$F$39<50,Ipotesi!$C$7,IF(Ipotesi!$F$39<150,Ipotesi!$C$8,Ipotesi!$C$9)) -> 15 | F11: =IF(Ipotesi!$F$39<50,Ipotesi!$C$7,IF(Ipotesi!$F$39<150,Ipotesi!$C$8,Ipotesi!$C$9)) -> 15 | G11: =IF(Ipotesi!$F$39<50,Ipotesi!$C$7,IF(Ipotesi!$F$39<150,Ipotesi!$C$8,Ipotesi!$C$9)) -> 15 | H11: =IF(Ipotesi!$F$39<50,Ipotesi!$C$7,IF(Ipotesi!$F$39<150,Ipotesi!$C$8,Ipotesi!$C$9)) -> 15 | I11: =IF(Ipotesi!$F$39<50,Ipotesi!$C$7,IF(Ipotesi!$F$39<150,Ipotesi!$C$8,Ipotesi!$C$9)) -> 15 | ... AK11: =IF(Ipotesi!$F$39<50,Ipotesi!$C$7,IF(Ipotesi!$F$39<150,Ipotesi!$C$8,Ipotesi!$C$9)) -> 15
A12: Ricavi canoni B2B | B12: =(B4+B8)*Ipotesi!$C$11+B9*B11 -> 0 | C12: =(C4+C8)*Ipotesi!$C$11+C9*C11 -> 0 | D12: =(D4+D8)*Ipotesi!$C$11+D9*D11 -> 0 | E12: =(E4+E8)*Ipotesi!$C$11+E9*E11 -> 0 | F12: =(F4+F8)*Ipotesi!$C$11+F9*F11 -> 0 | G12: =(G4+G8)*Ipotesi!$C$11+G9*G11 -> 0 | H12: =(H4+H8)*Ipotesi!$C$11+H9*H11 -> 1730 | I12: =(I4+I8)*Ipotesi!$C$11+I9*I11 -> 1730 | ... AK12: =(AK4+AK8)*Ipotesi!$C$11+AK9*AK11 -> 11038.108
A13: Ricavi verifiche al costo (FP) | B13: =(B4+B8)*Ipotesi!$C$10*Ipotesi!$C$16 -> 0 | C13: =(C4+C8)*Ipotesi!$C$10*Ipotesi!$C$16 -> 0 | D13: =(D4+D8)*Ipotesi!$C$10*Ipotesi!$C$16 -> 0 | E13: =(E4+E8)*Ipotesi!$C$10*Ipotesi!$C$16 -> 0 | F13: =(F4+F8)*Ipotesi!$C$10*Ipotesi!$C$16 -> 0 | G13: =(G4+G8)*Ipotesi!$C$10*Ipotesi!$C$16 -> 0 | H13: =(H4+H8)*Ipotesi!$C$10*Ipotesi!$C$16 -> 960 | I13: =(I4+I8)*Ipotesi!$C$10*Ipotesi!$C$16 -> 960 | ... AK13: =(AK4+AK8)*Ipotesi!$C$10*Ipotesi!$C$16 -> 2342.4
A14: Ricavi B2C | B14: =B7*Ipotesi!$C$17 -> 0 | C14: =C7*Ipotesi!$C$17 -> 0 | D14: =D7*Ipotesi!$C$17 -> 0 | E14: =E7*Ipotesi!$C$17 -> 0 | F14: =F7*Ipotesi!$C$17 -> 0 | G14: =G7*Ipotesi!$C$17 -> 0 | H14: =H7*Ipotesi!$C$17 -> 0 | I14: =I7*Ipotesi!$C$17 -> 0 | ... AK14: =AK7*Ipotesi!$C$17 -> 3251.6163
A15: RICAVI | B15: =B12+B13+B14 -> 0 | C15: =C12+C13+C14 -> 0 | D15: =D12+D13+D14 -> 0 | E15: =E12+E13+E14 -> 0 | F15: =F12+F13+F14 -> 0 | G15: =G12+G13+G14 -> 0 | H15: =H12+H13+H14 -> 2690 | I15: =I12+I13+I14 -> 2690 | ... AK15: =AK12+AK13+AK14 -> 16632.124
A16: NextPax | B16: =IF((B10+B7*Ipotesi!$C$18)>0,Ipotesi!$C$12+MAX(0,(B10+B7*Ipotesi!$C$18)-Ipotesi!$C$13)*Ipotesi!$C$14,0) -> 0 | C16: =IF((C10+C7*Ipotesi!$C$18)>0,Ipotesi!$C$12+MAX(0,(C10+C7*Ipotesi!$C$18)-Ipotesi!$C$13)*Ipotesi!$C$14,0) -> 0 | D16: =IF((D10+D7*Ipotesi!$C$18)>0,Ipotesi!$C$12+MAX(0,(D10+D7*Ipotesi!$C$18)-Ipotesi!$C$13)*Ipotesi!$C$14,0) -> 0 | E16: =IF((E10+E7*Ipotesi!$C$18)>0,Ipotesi!$C$12+MAX(0,(E10+E7*Ipotesi!$C$18)-Ipotesi!$C$13)*Ipotesi!$C$14,0) -> 0 | F16: =IF((F10+F7*Ipotesi!$C$18)>0,Ipotesi!$C$12+MAX(0,(F10+F7*Ipotesi!$C$18)-Ipotesi!$C$13)*Ipotesi!$C$14,0) -> 0 | G16: =IF((G10+G7*Ipotesi!$C$18)>0,Ipotesi!$C$12+MAX(0,(G10+G7*Ipotesi!$C$18)-Ipotesi!$C$13)*Ipotesi!$C$14,0) -> 0 | H16: =IF((H10+H7*Ipotesi!$C$18)>0,Ipotesi!$C$12+MAX(0,(H10+H7*Ipotesi!$C$18)-Ipotesi!$C$13)*Ipotesi!$C$14,0) -> 980 | I16: =IF((I10+I7*Ipotesi!$C$18)>0,Ipotesi!$C$12+MAX(0,(I10+I7*Ipotesi!$C$18)-Ipotesi!$C$13)*Ipotesi!$C$14,0) -> 980 | ... AK16: =IF((AK10+AK7*Ipotesi!$C$18)>0,Ipotesi!$C$12+MAX(0,(AK10+AK7*Ipotesi!$C$18)-Ipotesi!$C$13)*Ipotesi!$C$14,0) -> 4251.9362
A17: SDI, AI, video | B17: =B10*Ipotesi!$C$15 -> 0 | C17: =C10*Ipotesi!$C$15 -> 0 | D17: =D10*Ipotesi!$C$15 -> 0 | E17: =E10*Ipotesi!$C$15 -> 0 | F17: =F10*Ipotesi!$C$15 -> 0 | G17: =G10*Ipotesi!$C$15 -> 0 | H17: =H10*Ipotesi!$C$15 -> 100 | I17: =I10*Ipotesi!$C$15 -> 100 | ... AK17: =AK10*Ipotesi!$C$15 -> 425.78421
A18: Verifiche d'identità | B18: =B10*Ipotesi!$C$10*Ipotesi!$C$16 -> 0 | C18: =C10*Ipotesi!$C$10*Ipotesi!$C$16 -> 0 | D18: =D10*Ipotesi!$C$10*Ipotesi!$C$16 -> 0 | E18: =E10*Ipotesi!$C$10*Ipotesi!$C$16 -> 0 | F18: =F10*Ipotesi!$C$10*Ipotesi!$C$16 -> 0 | G18: =G10*Ipotesi!$C$10*Ipotesi!$C$16 -> 0 | H18: =H10*Ipotesi!$C$10*Ipotesi!$C$16 -> 960 | I18: =I10*Ipotesi!$C$10*Ipotesi!$C$16 -> 960 | ... AK18: =AK10*Ipotesi!$C$10*Ipotesi!$C$16 -> 4087.5284
A19: Costi variabili B2C | B19: =B7*Ipotesi!$C$18*Ipotesi!$C$15 -> 0 | C19: =C7*Ipotesi!$C$18*Ipotesi!$C$15 -> 0 | D19: =D7*Ipotesi!$C$18*Ipotesi!$C$15 -> 0 | E19: =E7*Ipotesi!$C$18*Ipotesi!$C$15 -> 0 | F19: =F7*Ipotesi!$C$18*Ipotesi!$C$15 -> 0 | G19: =G7*Ipotesi!$C$18*Ipotesi!$C$15 -> 0 | H19: =H7*Ipotesi!$C$18*Ipotesi!$C$15 -> 0 | I19: =I7*Ipotesi!$C$18*Ipotesi!$C$15 -> 0 | ... AK19: =AK7*Ipotesi!$C$18*Ipotesi!$C$15 -> 89.69976
A20: MARGINE LORDO | B20: =B15-B16-B17-B18-B19 -> 0 | C20: =C15-C16-C17-C18-C19 -> 0 | D20: =D15-D16-D17-D18-D19 -> 0 | E20: =E15-E16-E17-E18-E19 -> 0 | F20: =F15-F16-F17-F18-F19 -> 0 | G20: =G15-G16-G17-G18-G19 -> 0 | H20: =H15-H16-H17-H18-H19 -> 650 | I20: =I15-I16-I17-I18-I19 -> 650 | ... AK20: =AK15-AK16-AK17-AK18-AK19 -> 7777.1754
A21: Costi fissi | B21: =IF(B3=1,Ipotesi!$C$22+Ipotesi!$C$23+Ipotesi!$C$29,Ipotesi!$C$21)+IF(B2>=Ipotesi!$C$26,Ipotesi!$C$24+Ipotesi!$C$25,0)+IF(B2=Ipotesi!$C$28,Ipotesi!$C$27,0) -> 205 | C21: =IF(C3=1,Ipotesi!$C$22+Ipotesi!$C$23+Ipotesi!$C$29,Ipotesi!$C$21)+IF(C2>=Ipotesi!$C$26,Ipotesi!$C$24+Ipotesi!$C$25,0)+IF(C2=Ipotesi!$C$28,Ipotesi!$C$27,0) -> 455 | D21: =IF(D3=1,Ipotesi!$C$22+Ipotesi!$C$23+Ipotesi!$C$29,Ipotesi!$C$21)+IF(D2>=Ipotesi!$C$26,Ipotesi!$C$24+Ipotesi!$C$25,0)+IF(D2=Ipotesi!$C$28,Ipotesi!$C$27,0) -> 6455 | E21: =IF(E3=1,Ipotesi!$C$22+Ipotesi!$C$23+Ipotesi!$C$29,Ipotesi!$C$21)+IF(E2>=Ipotesi!$C$26,Ipotesi!$C$24+Ipotesi!$C$25,0)+IF(E2=Ipotesi!$C$28,Ipotesi!$C$27,0) -> 455 | F21: =IF(F3=1,Ipotesi!$C$22+Ipotesi!$C$23+Ipotesi!$C$29,Ipotesi!$C$21)+IF(F2>=Ipotesi!$C$26,Ipotesi!$C$24+Ipotesi!$C$25,0)+IF(F2=Ipotesi!$C$28,Ipotesi!$C$27,0) -> 455 | G21: =IF(G3=1,Ipotesi!$C$22+Ipotesi!$C$23+Ipotesi!$C$29,Ipotesi!$C$21)+IF(G2>=Ipotesi!$C$26,Ipotesi!$C$24+Ipotesi!$C$25,0)+IF(G2=Ipotesi!$C$28,Ipotesi!$C$27,0) -> 455 | H21: =IF(H3=1,Ipotesi!$C$22+Ipotesi!$C$23+Ipotesi!$C$29,Ipotesi!$C$21)+IF(H2>=Ipotesi!$C$26,Ipotesi!$C$24+Ipotesi!$C$25,0)+IF(H2=Ipotesi!$C$28,Ipotesi!$C$27,0) -> 945 | I21: =IF(I3=1,Ipotesi!$C$22+Ipotesi!$C$23+Ipotesi!$C$29,Ipotesi!$C$21)+IF(I2>=Ipotesi!$C$26,Ipotesi!$C$24+Ipotesi!$C$25,0)+IF(I2=Ipotesi!$C$28,Ipotesi!$C$27,0) -> 945 | ... AK21: =IF(AK3=1,Ipotesi!$C$22+Ipotesi!$C$23+Ipotesi!$C$29,Ipotesi!$C$21)+IF(AK2>=Ipotesi!$C$26,Ipotesi!$C$24+Ipotesi!$C$25,0)+IF(AK2=Ipotesi!$C$28,Ipotesi!$C$27,0) -> 945
A22: Persone | B22: =B3*Ipotesi!$F$44+IF(AND(Ipotesi!$F$45>0,B10>=Ipotesi!$F$45),Ipotesi!$F$46,0) -> 0 | C22: =C3*Ipotesi!$F$44+IF(AND(Ipotesi!$F$45>0,C10>=Ipotesi!$F$45),Ipotesi!$F$46,0) -> 0 | D22: =D3*Ipotesi!$F$44+IF(AND(Ipotesi!$F$45>0,D10>=Ipotesi!$F$45),Ipotesi!$F$46,0) -> 0 | E22: =E3*Ipotesi!$F$44+IF(AND(Ipotesi!$F$45>0,E10>=Ipotesi!$F$45),Ipotesi!$F$46,0) -> 0 | F22: =F3*Ipotesi!$F$44+IF(AND(Ipotesi!$F$45>0,F10>=Ipotesi!$F$45),Ipotesi!$F$46,0) -> 0 | G22: =G3*Ipotesi!$F$44+IF(AND(Ipotesi!$F$45>0,G10>=Ipotesi!$F$45),Ipotesi!$F$46,0) -> 0 | H22: =H3*Ipotesi!$F$44+IF(AND(Ipotesi!$F$45>0,H10>=Ipotesi!$F$45),Ipotesi!$F$46,0) -> 0 | I22: =I3*Ipotesi!$F$44+IF(AND(Ipotesi!$F$45>0,I10>=Ipotesi!$F$45),Ipotesi!$F$46,0) -> 0 | ... AK22: =AK3*Ipotesi!$F$44+IF(AND(Ipotesi!$F$45>0,AK10>=Ipotesi!$F$45),Ipotesi!$F$46,0) -> 3000
A23: EBITDA | B23: =B20-B21-B22 -> -205 | C23: =C20-C21-C22 -> -455 | D23: =D20-D21-D22 -> -6455 | E23: =E20-E21-E22 -> -455 | F23: =F20-F21-F22 -> -455 | G23: =G20-G21-G22 -> -455 | H23: =H20-H21-H22 -> -295 | I23: =I20-I21-I22 -> -295 | ... AK23: =AK20-AK21-AK22 -> 3832.1754
A24: Anticipo annuale FP (cassa) | B24: =IF(AND(B3=1,MOD(B2-Ipotesi!$F$32,12)=0),B4*Ipotesi!$C$11*12,0)-B4*Ipotesi!$C$11 -> 0 | C24: =IF(AND(C3=1,MOD(C2-Ipotesi!$F$32,12)=0),C4*Ipotesi!$C$11*12,0)-C4*Ipotesi!$C$11 -> 0 | D24: =IF(AND(D3=1,MOD(D2-Ipotesi!$F$32,12)=0),D4*Ipotesi!$C$11*12,0)-D4*Ipotesi!$C$11 -> 0 | E24: =IF(AND(E3=1,MOD(E2-Ipotesi!$F$32,12)=0),E4*Ipotesi!$C$11*12,0)-E4*Ipotesi!$C$11 -> 0 | F24: =IF(AND(F3=1,MOD(F2-Ipotesi!$F$32,12)=0),F4*Ipotesi!$C$11*12,0)-F4*Ipotesi!$C$11 -> 0 | G24: =IF(AND(G3=1,MOD(G2-Ipotesi!$F$32,12)=0),G4*Ipotesi!$C$11*12,0)-G4*Ipotesi!$C$11 -> 0 | H24: =IF(AND(H3=1,MOD(H2-Ipotesi!$F$32,12)=0),H4*Ipotesi!$C$11*12,0)-H4*Ipotesi!$C$11 -> 19030 | I24: =IF(AND(I3=1,MOD(I2-Ipotesi!$F$32,12)=0),I4*Ipotesi!$C$11*12,0)-I4*Ipotesi!$C$11 -> -1730 | ... AK24: =IF(AND(AK3=1,MOD(AK2-Ipotesi!$F$32,12)=0),AK4*Ipotesi!$C$11*12,0)-AK4*Ipotesi!$C$11 -> -1730
A25: Cassa cumulata | B25: =0+B23+B24 -> -205 | C25: =B25+C23+C24 -> -660 | D25: =C25+D23+D24 -> -7115 | E25: =D25+E23+E24 -> -7570 | F25: =E25+F23+F24 -> -8025 | G25: =F25+G23+G24 -> -8480 | H25: =G25+H23+H24 -> 10255 | I25: =H25+I23+I24 -> 8230 | J25: =I25+J23+J24 -> 6285.88 | ... AK25: =AJ25+AK23+AK24 -> 74285.694

Sheet Sintesi
A1: Sintesi annuale dello scenario attivo
B2: Anno 1 (nov 26-ott 27) | C2: Anno 2 | D2: Anno 3
A3: Unità B2B a fine anno | B3: =Mensile!M10 -> 346 | C3: =Mensile!Y10 -> 610 | D3: =Mensile!AK10 -> 1064.4605
A4: Host B2C a fine anno | B4: =Mensile!M7 -> 17.4654 | C4: =Mensile!Y7 -> 73.349762 | D4: =Mensile!AK7 -> 112.1247
A5: Ricavi | B5: =SUM(Mensile!B15:M15) -> 19745.677 | C5: =SUM(Mensile!N15:Y15) -> 81759.096 | D5: =SUM(Mensile!Z15:AK15) -> 157131.37
A6: Margine lordo | B6: =SUM(Mensile!B20:M20) -> 5481.5503 | C6: =SUM(Mensile!N20:Y20) -> 30898.283 | D6: =SUM(Mensile!Z20:AK20) -> 70355.861
A7: Costi fissi | B7: =SUM(Mensile!B21:M21) -> 14150 | C7: =SUM(Mensile!N21:Y21) -> 11340 | D7: =SUM(Mensile!Z21:AK21) -> 11340
A8: Persone | B8: =SUM(Mensile!B22:M22) -> 0 | C8: =SUM(Mensile!N22:Y22) -> 0 | D8: =SUM(Mensile!Z22:AK22) -> 6000
A9: EBITDA | B9: =SUM(Mensile!B23:M23) -> -8668.4497 | C9: =SUM(Mensile!N23:Y23) -> 19558.283 | D9: =SUM(Mensile!Z23:AK23) -> 53015.861
A10: Ricavi mensili a fine anno | B10: =Mensile!M15 -> 4229.4566 | C10: =Mensile!Y15 -> 8690.7431 | D10: =Mensile!AK15 -> 16632.124
A11: Cassa cumulata a fine anno | B11: =Mensile!M25 -> 1711.5503 | C11: =Mensile!Y25 -> 21269.833 | D11: =Mensile!AK25 -> 74285.694
A13: Cassa cumulata minima | B13: =MIN(0,MIN(Mensile!B25:AK25)) -> -8480
